django_web_repl/__init__.py
django_web_repl/apps.py
django_web_repl/models.py
django_web_repl/signals.py
django_web_repl/static/django_web_shell/css/.gitkeep
django_web_repl/static/django_web_shell/images/.gitkeep
django_web_repl/static/django_web_shell/js/.gitkeep
django_web_repl/templates/django_web_shell/.gitkeep
django_web_repl/urls.py
django_web_repl-0.0.1.dist-info/LICENSE
django_web_repl-0.0.1.dist-info/METADATA
django_web_repl-0.0.1.dist-info/WHEEL
django_web_repl-0.0.1.dist-info/RECORD
