Metadata-Version: 2.1
Name: django-web-repl
Version: 0.0.1
Summary: 
License: MIT
Author: Dani Hodovic
Author-email: you@example.com
Requires-Python: >=3.9
Classifier: License :: OSI Approved :: MIT License
Classifier: Programming Language :: Python :: 3
Classifier: Programming Language :: Python :: 3.9
Classifier: Programming Language :: Python :: 3.10
Classifier: Programming Language :: Python :: 3.11
Classifier: Programming Language :: Python :: 3.12
Requires-Dist: Django (>=4)
Requires-Dist: channels (>=4.0.0,<5.0.0)
